sfft/AutoCrowdedPrep.py
sfft/AutoSparsePrep.py
sfft/BSplineSFFT.py
sfft/CustomizedPacket.py
sfft/EasyCrowdedPacket.py
sfft/EasySparsePacket.py
sfft/MultiEasyCrowdedPacket.py
sfft/MultiEasySparsePacket.py
sfft/PureCupyCustomizedPacket.py
sfft/__init__.py
sfft/sfftcore/SFFTConfigure.py
sfft/sfftcore/SFFTSubtract.py
sfft/sfftcore/__init__.py
sfft/utils/CombineHeader.py
sfft/utils/ConvKernelConvertion.py
sfft/utils/DeCorrelationCalculator.py
sfft/utils/HoughDetection.py
sfft/utils/HoughMorphClassifier.py
sfft/utils/ImageZoomRotate.py
sfft/utils/NeighboringPixelCovariance.py
sfft/utils/PatternRotationCalculator.py
sfft/utils/PureCupyDeCorrelationCalculator.py
sfft/utils/PureCupyFFTKits.py
sfft/utils/ReadWCS.py
sfft/utils/SExSkySubtract.py
sfft/utils/SFFTSolutionReader.py
sfft/utils/SkyLevelEstimator.py
sfft/utils/StampGenerator.py
sfft/utils/SymmetricMatch.py
sfft/utils/WeightedQuantile.py
sfft/utils/__init__.py
sfft/utils/meta/MultiProc.py
sfft/utils/meta/TimeoutKit.py
sfft/utils/meta/__init__.py
sfft/utils/pyAstroMatic/AMConfigMaker.py
sfft/utils/pyAstroMatic/PYSEx.py
sfft/utils/pyAstroMatic/PYSWarp.py
sfft/utils/pyAstroMatic/__init__.py
sfft-1.6.4.dist-info/licenses/LICENSE
sfft-1.6.4.dist-info/METADATA
sfft-1.6.4.dist-info/WHEEL
sfft-1.6.4.dist-info/top_level.txt
sfft-1.6.4.dist-info/RECORD
